quaternion/numba_wrapper.py
quaternion/__init__.py
quaternion/numpy_quaternion.cpython-312-darwin.so
quaternion/quaternion_time_series.py
quaternion/calculus.py
quaternion/means.py
numpy_quaternion-2024.0.12.dist-info/RECORD
numpy_quaternion-2024.0.12.dist-info/WHEEL
numpy_quaternion-2024.0.12.dist-info/top_level.txt
numpy_quaternion-2024.0.12.dist-info/METADATA
