Metadata-Version: 2.4
Name: numpy-quaternion
Version: 2024.0.12
Summary: Add a quaternion dtype to NumPy
Home-page: https://github.com/moble/quaternion
Author: Michael Boyle
Author-email: Michael Boyle <michael.oliver.boyle@gmail.com>
License: The MIT License (MIT)
Project-URL: Homepage, https://github.com/moble/quaternion
Project-URL: Documentation, https://quaternion.readthedocs.io/en/latest
Classifier: License :: OSI Approved :: MIT License
Classifier: Development Status :: 5 - Production/Stable
Classifier: Programming Language :: Python :: 3
Classifier: Operating System :: OS Independent
Classifier: Intended Audience :: Science/Research
Classifier: Topic :: Scientific/Engineering :: Physics
Classifier: Topic :: Scientific/Engineering :: Astronomy
Requires-Python: <3.14,>=3.10
Requires-Dist: numpy<3,>=1.25
Requires-Dist: scipy<2,>=1.5
Provides-Extra: docs
Requires-Dist: mkdocs-material; extra == "docs"
Requires-Dist: mkdocstrings-python; extra == "docs"
Requires-Dist: pymdown-extensions; extra == "docs"
Dynamic: author
Dynamic: home-page
